dedal/__init__.py
dedal/bll/SpackManager.py
dedal/bll/__init__.py
dedal/bll/cli_utils.py
dedal/build_cache/BuildCacheManagerCreator.py
dedal/build_cache/BuildCacheManagerInterface.py
dedal/build_cache/BuildCacheManagerOci.py
dedal/build_cache/BuildCacheManagerOciDefault.py
dedal/build_cache/CachedBuildResultUploader.py
dedal/build_cache/CachedBuildResultsFetcher.py
dedal/build_cache/CachedSourceFetcher.py
dedal/build_cache/CachedSourceUploader.py
dedal/build_cache/SpecfileBuildStoragePathExtractor.py
dedal/build_cache/SpecfileDagHash.py
dedal/build_cache/SpecfileSourceStoragePathExtractor.py
dedal/build_cache/__init__.py
dedal/cli/__init__.py
dedal/cli/fetch_cached_buildresults.py
dedal/cli/fetch_cached_sources.py
dedal/cli/spack_manager_api.py
dedal/cli/specfile_dag_hash.py
dedal/cli/specfile_storage_path_build.py
dedal/cli/specfile_storage_path_source.py
dedal/cli/update_cached_buildresults.py
dedal/cli/update_cached_sources.py
dedal/configuration/GpgConfig.py
dedal/configuration/SpackConfig.py
dedal/configuration/__init__.py
dedal/enum/SpackCacheStorageEnum.py
dedal/enum/SpackConfigCommand.py
dedal/enum/SpackViewEnum.py
dedal/enum/__init__.py
dedal/error_handling/__init__.py
dedal/error_handling/exceptions.py
dedal/logger/__init__.py
dedal/logger/logger_builder.py
dedal/logger/logging.conf
dedal/model/SpackDescriptor.py
dedal/model/__init__.py
dedal/serialize/PickleSerializer.py
dedal/serialize/SerializeInterface.py
dedal/serialize/__init__.py
dedal/spack_factory/SpackCacheOperation.py
dedal/spack_factory/SpackEnvOperation.py
dedal/spack_factory/SpackOperation.py
dedal/spack_factory/SpackOperationCreateCache.py
dedal/spack_factory/SpackOperationCreator.py
dedal/spack_factory/SpackOperationUseCache.py
dedal/spack_factory/SpackToolOperation.py
dedal/spack_factory/__init__.py
dedal/tests/__init__.py
dedal/tests/testing_variables.py
dedal/tests/integration_tests/__init__.py
dedal/tests/integration_tests/helper.py
dedal/tests/integration_tests/serialize_test.py
dedal-1.0.0.dist-info/licenses/LICENSE
dedal-1.0.0.dist-info/METADATA
dedal-1.0.0.dist-info/WHEEL
dedal-1.0.0.dist-info/entry_points.txt
dedal-1.0.0.dist-info/top_level.txt
dedal-1.0.0.dist-info/RECORD
