Metadata-Version: 2.4
Name: dedal
Version: 1.0.0
Summary: This package includes all the essential tools required to set up an EBRAINS Software Distribution environment.
Author: Adrian Ciu, Eleni Mathioulaki, Eric Müller, Jithu Murugan, Lia Domide, Wouter Klijn
Maintainer-email: Brainiacs <science@codemart.ro>
License: 
Project-URL: Source, https://gitlab.ebrains.eu/ri/tech-hub/platform/esd/dedal
Keywords: spack,package,packaging,environment,cache,caching,esd
Requires-Python: >=3.10
License-File: LICENSE
Requires-Dist: oras
Requires-Dist: ruamel.yaml
Requires-Dist: click
Requires-Dist: jsonpickle
Requires-Dist: pyyaml
Provides-Extra: test
Requires-Dist: pytest; extra == "test"
Requires-Dist: pytest-mock; extra == "test"
Requires-Dist: pytest-ordering; extra == "test"
Requires-Dist: coverage; extra == "test"
Dynamic: license-file
